mathsom/__init__.py
mathsom/interpolations.py
mathsom/numerics.py
mathsom/solvers.py
mathsom-0.1.6.dist-info/LICENSE
mathsom-0.1.6.dist-info/METADATA
mathsom-0.1.6.dist-info/WHEEL
mathsom-0.1.6.dist-info/top_level.txt
mathsom-0.1.6.dist-info/RECORD
