Metadata-Version: 2.1
Name: mathsom
Version: 0.1.6
Summary: Personal library for math related problems
Home-page: https://github.com/oliverm91/mathsom
Author: Oliver Mohr B.
Author-email: oliver.mohr.b@gmail.com
License: UNKNOWN
Keywords: solvers,solver,interpolations,interpolation,numerics,derivatives,integrals
Platform: UNKNOWN
Classifier: Development Status :: 3 - Alpha
Classifier: License :: OSI Approved :: GNU General Public License v3 (GPLv3)
Classifier: Programming Language :: Python
Classifier: Programming Language :: Python :: 3.8
Classifier: Programming Language :: Python :: 3.9
Classifier: Programming Language :: Python :: 3.10
Classifier: Programming Language :: Python :: 3.11
Classifier: Topic :: Scientific/Engineering :: Mathematics
Classifier: Natural Language :: English
Requires-Python: >=3.8
Requires-Dist: numpy
Requires-Dist: scipy
Requires-Dist: auxfuncs
